aws2fa/__init__.py
aws2fa/_version.py
aws2fa/bin.py
aws2fa/core.py
aws2fa/exceptions.py
aws2fa/helpers.py
aws2fa-0.0.3.dist-info/DESCRIPTION.rst
aws2fa-0.0.3.dist-info/METADATA
aws2fa-0.0.3.dist-info/RECORD
aws2fa-0.0.3.dist-info/WHEEL
aws2fa-0.0.3.dist-info/entry_points.txt
aws2fa-0.0.3.dist-info/metadata.json
aws2fa-0.0.3.dist-info/top_level.txt
