Metadata-Version: 2.0
Name: aws2fa
Version: 0.0.3
Summary: aws2fa is a simple command line tool to handle 2fa authentication respecting aws-cli standard patterns
Home-page: https://github.com/jorgebastida/aws2fa
Author: Jorge Bastida
Author-email: me@jorgebastida.com
License: BSD
Keywords: aws 2fa auth authentication awscli
Platform: any
Classifier: Programming Language :: Python :: 3
Classifier: Programming Language :: Python :: 2
Classifier: Development Status :: 4 - Beta
Classifier: Environment :: Web Environment
Classifier: Intended Audience :: Developers
Classifier: License :: OSI Approved :: BSD License
Classifier: Operating System :: OS Independent
Classifier: Topic :: Utilities
Requires-Dist: boto3 (>=1.4)
Requires-Dist: argparse (>=1.1.0); python_version in "2.4, 2.5, 2.6"
